LICENSE
MANIFEST.in
README.rst
setup.py
docs/AUTHORS.rst
docs/CHANGELOG.rst
docs/CONTRIBUTING.rst
docs/PULLREQUEST.rst
docs/spelling_wordlist.txt
docs/rst/authors.rst
docs/rst/changelog.rst
docs/rst/conf.py
docs/rst/contributing.rst
docs/rst/index.rst
docs/rst/installation.rst
docs/rst/readme.rst
docs/rst/spelling_wordlist.txt
docs/rst/usage.rst
docs/rst/reference/index.rst
docs/rst/reference/py30303_disc.rst
docs/rst/reference/py30303_disc_libs.rst
src/py30303_disc/__init__.py
src/py30303_disc/__main__.py
src/py30303_disc/d30303_discover.py
src/py30303_disc.egg-info/PKG-INFO
src/py30303_disc.egg-info/SOURCES.txt
src/py30303_disc.egg-info/dependency_links.txt
src/py30303_disc.egg-info/entry_points.txt
src/py30303_disc.egg-info/not-zip-safe
src/py30303_disc.egg-info/top_level.txt
src/py30303_disc/libs/__init__.py
src/py30303_disc/libs/py30303_disc.py