Metadata-Version: 2.1
Name: py30303-disc
Version: 0.3.0
Summary: UDP 30303 Network discovery library.
Home-page: https://github.com/garbled1/py30303_disc
Author: Tim Rightnour
Author-email: the@garbled.one
License: Apache 2.0
Project-URL: webpage, https://github.com/garbled1/py30303_disc
Project-URL: Documentation, https://py30303_disc.readthedocs.io/en/latest/
Project-URL: Changelog, https://github.com/garbled1/py30303_disc/blob/master/docs/CHANGELOG.rst
Project-URL: Issue Tracker, https://github.com/garbled1/py30303_disc/issues
Project-URL: Discussion Forum, https://github.com/garbled1/py30303_disc/discussions
Keywords: udp,discovery,30303
Platform: UNKNOWN
Classifier: Development Status :: 3 - Alpha
Classifier: License :: OSI Approved :: Apache Software License
Classifier: License :: OSI Approved :: MIT License
Classifier: Intended Audience :: Developers
Classifier: Natural Language :: English
Classifier: Operating System :: POSIX
Classifier: Programming Language :: Python :: 3 :: Only
Classifier: Topic :: Software Development :: Libraries :: Python Modules
Requires-Python: >=3.6, <3.10
License-File: LICENSE
